emid/__init__.py
emid/__main__.py
emid/_version_info.py
emid/audio_manager.py
emid/dialog_edit_preferences.py
emid/dialog_edit_transducers.py
emid/global_parameters.py
emid/multirate.py
emid/pyqtver.py
emid/qrc_resources.py
emid/sndlib.py
emid/utils_redirect_stream_to_file.py
emid/wavpy.py
emid/wavpy_sndf.py
emid/doc/Makefile
emid/doc/calibration.rst
emid/doc/conf.py
emid/doc/experiment_setup.rst
emid/doc/index.rst
emid/doc/installation.rst
emid/doc/intro.rst
emid/doc/make.bat
emid/doc/mkdoc.sh
emid/doc/requirements.txt
emid/doc/Figures/edit_transducers.png
emid/doc/Figures/emid_screenshot.png
emid/doc/Figures/example_trial_list.png
emid-0.0.10.dist-info/COPYING.txt
emid-0.0.10.dist-info/METADATA
emid-0.0.10.dist-info/WHEEL
emid-0.0.10.dist-info/entry_points.txt
emid-0.0.10.dist-info/top_level.txt
emid-0.0.10.dist-info/RECORD
