Metadata-Version: 2.1
Name: emid
Version: 0.0.10
Summary: emid is a software for running a voice emotion identification experiment
Author-email: Samuele Carcagno <sam.carcagno@gmail.com>
License: GNU GENERAL PUBLIC LICENSE
Project-URL: Homepage, https://gitlab.com/sam81/emid
Project-URL: Bug Tracker, https://gitlab.com/sam81/emid/-/issues
Classifier: Programming Language :: Python :: 3
Classifier: License :: OSI Approved :: GNU General Public License v3 (GPLv3)
Classifier: Operating System :: OS Independent
Classifier: Development Status :: 3 - Alpha
Classifier: Environment :: X11 Applications :: Qt
Classifier: Intended Audience :: Developers
Classifier: Operating System :: MacOS :: MacOS X
Classifier: Operating System :: Microsoft :: Windows
Classifier: Operating System :: POSIX
Classifier: Topic :: Scientific/Engineering
Requires-Python: >=3.7
License-File: COPYING.txt
Requires-Dist: numpy >=1.0.0
Requires-Dist: pandas >=1.0.0
Requires-Dist: PyAudio >=0.2.11
Requires-Dist: PyQt6 >=6.6.0
Requires-Dist: scipy >=1.0.1
Requires-Dist: soundfile >=0.10.1
